pyinsight_archiver_gcs/__init__.py
pyinsight_archiver_gcs/gcs_archiver.py
pyinsight_archiver_gcs-0.0.6.dist-info/LICENSE
pyinsight_archiver_gcs-0.0.6.dist-info/METADATA
pyinsight_archiver_gcs-0.0.6.dist-info/WHEEL
pyinsight_archiver_gcs-0.0.6.dist-info/top_level.txt
pyinsight_archiver_gcs-0.0.6.dist-info/RECORD
