Metadata-Version: 2.1
Name: pyinsight-archiver-gcs
Version: 0.0.6
Summary: Insight Archiver Module Google Cloud Storage with Parquet Support
Home-page: https://github.com/X-I-A/pyinsight-archiver-gcs
Author: Soral
Author-email: soral@x-i-a.com
License: UNKNOWN
Platform: UNKNOWN
Classifier: Programming Language :: Python :: 3
Classifier: License :: OSI Approved :: GNU General Public License v3 (GPLv3)
Classifier: Operating System :: OS Independent
Requires-Python: >=3.5
Requires-Dist: pyinsight
Requires-Dist: google-cloud-storagegoogle-auth
Requires-Dist: gcsfs
Requires-Dist: pandas
Requires-Dist: pyarrow
